{
  "project_info": {
    "project_number": "821995047118",
    "firebase_url": "https://admin-college-app-df5b0-default-rtdb.firebaseio.com",
    "project_id": "admin-college-app-df5b0",
    "storage_bucket": "admin-college-app-df5b0.appspot.com"
  },
  "client": [
    {
      "client_info": {
        "mobilesdk_app_id": "1:821995047118:android:6076dfcce8949b086da89f",
        "android_client_info": {
          "package_name": "com.example.admincollegeapp"
        }
      },
      "oauth_client": [],
      "api_key": [
        {
          "current_key": ""
        }
      ],
      "services": {
        "appinvite_service": {
          "other_platform_oauth_client": []
        }
      }
    },
    {
      "client_info": {
        "mobilesdk_app_id": "1:821995047118:android:b99fbe4c61590cab6da89f",
        "android_client_info": {
          "package_name": "com.example.collegeapp"
        }
      },
      "oauth_client": [],
      "api_key": [
        {
          "current_key": "AIzaSyDpNTTIOMfuaTWEQqx-mZkv2q0R_v5UJdA"
        }
      ],
      "services": {
        "appinvite_service": {
          "other_platform_oauth_client": []
        }
      }
    }
  ],
  "configuration_version": "1"
}
